typyst/__init__.py
typyst/gen.py
typyst/naming.py
typyst/pronounceable_mapping.py
typyst/regex_with_defaults.py
typyst/table.py
typyst/to.py
typyst/trans.py
typyst-0.0.3.dist-info/LICENSE
typyst-0.0.3.dist-info/METADATA
typyst-0.0.3.dist-info/WHEEL
typyst-0.0.3.dist-info/top_level.txt
typyst-0.0.3.dist-info/RECORD
