Metadata-Version: 2.1
Name: typyst
Version: 0.0.3
Summary: Utils to manipulate strings
Home-page: https://github.com/thorwhalen/newut/tree/master/typyst
Author: Thor Whalen
License: mit
Platform: any
License-File: LICENSE
